[{"_id":"66fcfa7ceeae229fd49f9340","createdAt":"2024-01-26T17:18:00+03:00","ticket":{"document":{"receipt":{"code":3,"user":"ООО \"Камелот-А\"","items":[{"nds":1,"sum":3299,"name":"Orbit Белоснежный Bubblemint 13,6г","price":3299,"quantity":1,"paymentType":4,"productType":1,"itemsQuantityMeasure":0},{"nds":1,"sum":2999,"name":"Американо","price":2999,"quantity":1,"paymentType":4,"productType":1,"itemsQuantityMeasure":0}],"nds18":1050,"fnsUrl":"www.nalog.gov.ru","region":"70","userInn":"7017187800  ","dateTime":"2024-01-26T17:18:00","kktRegId":"0006400488059532    ","metadata":{"id":5138262962545904641,"ofdId":"ofd9","address":"634034,Россия,Томская область,город Томск г.о.,,Томск г,,Нахимова ул,,д. 38,,,помещение пом.4,7 часть.пом .№3,","subtype":"receipt","receiveDate":"1970-01-01T00:00:00Z"},"operator":"Кассир: Андреева М. Б.","totalSum":6298,"creditSum":0,"numberKkt":"0609990012062114","fiscalSign":2390528800,"prepaidSum":0,"retailPlace":"Магазин \"Ярче\"","shiftNumber":283,"cashTotalSum":0,"provisionSum":0,"ecashTotalSum":6298,"operationType":1,"redefine_mask":0,"requestNumber":792,"fiscalDriveNumber":"7282440500256748","messageFiscalSign":9.297199763082365e+18,"retailPlaceAddress":"636034, Томская область, г. Томск, ул. Нахимова, д.38","appliedTaxationType":1,"fiscalDocumentNumber":189337,"fiscalDocumentFormatVer":4,"user_data":{"id":"22836224","promo_id":"","date_scan":"2024-01-27 13:19:55","date_create":""},"taxationType":1}}}}]