[{"_id":"e406c356d53c3568bca36b41","createdAt":"2024-09-22T16:00:00+03:00","ticket":{"document":{"receipt":{"code":3,"user":"ОБЩЕСТВО С ОГРАНИЧЕННОЙ ОТВЕТСТВЕННОСТЬЮ \"РОЗНИЦА К-1\"","items":[{"nds":1,"sum":300,"name":"                          СПИЧКИ","price":300,"quantity":1,"paymentType":4,"productType":1,"itemsQuantityMeasure":0},{"nds":1,"sum":19700,"name":"[M]СИГАРЕТЫ ВИНСТОН ИКС ЭС КОМПА","price":19700,"quantity":1,"paymentType":4,"productType":31,"productCodeNew":{"kmk":{"gtin":"00000046254856","sernum":"m=Zixjr","productIdType":10,"rawProductCode":"010000004625485621m=Zixjr"}},"labelCodeProcesMode":0,"itemsIndustryDetails":[{"idFoiv":"030","industryPropValue":"UUID=20ca9801-e9fe-4e4f-8b49-696d5bc35c3f&Time=1726995627992","foundationDocNumber":"1944","foundationDocDateTime":"21.11.2023"}],"itemsQuantityMeasure":0,"checkingProdInformationResult":15}],"nds18":3333,"region":"70","userInn":"2225074005  ","dateTime":"2024-09-22T16:00:00","kktRegId":"0001492717012958    ","metadata":{"id":5486076651534646784,"ofdId":"ofd9","address":"634033,Россия,Томская область,город Томск г.о.,,Томск г,,Богдана Хмельницкого ул,,д. 42Б,,,,","subtype":"receipt","receiveDate":"2024-09-22T09:00:49Z"},"operator":"Кассир Булгакова Анна","totalSum":20000,"creditSum":0,"numberKkt":"00106307422972","fiscalSign":239568884,"prepaidSum":0,"operatorInn":"700001716283","retailPlace":"Магазин \"Мария-Ра\" №982","shiftNumber":363,"cashTotalSum":0,"provisionSum":0,"ecashTotalSum":20000,"operationType":1,"redefine_mask":2,"requestNumber":268,"fiscalDriveNumber":"7284440700315887","messageFiscalSign":9.297139094191346e+18,"retailPlaceAddress":"634033, Томск г, Богдана Хмельницкого ул, д 42Б","appliedTaxationType":1,"buyerPhoneOrAddress":"check@maria-ra.ru","fiscalDocumentNumber":127554,"fiscalDocumentFormatVer":4,"checkingLabeledProdResult":0,"user_data":{"id":"25714125","promo_id":"","date_scan":"2024-09-22 12:55:08","date_create":""},"taxationType":1}}}}]