[{"_id":"7e48e6fddf0bd6ac6c26bf8d","createdAt":"2025-01-28T03:49:00+03:00","ticket":{"document":{"receipt":{"code":3,"nds0":0,"user":"ОБЩЕСТВО С ОГРАНИЧЕННОЙ ОТВЕТСТВЕННОСТЬЮ \"ЯНДЕКС.ТАКСИ\"","items":[{"nds":6,"sum":25600,"name":"Перевозка пассажиров и багажа","price":25600,"quantity":1,"paymentType":4,"productType":1,"providerInn":"700601740520","labelCodeProcesMode":0,"itemsQuantityMeasure":0,"paymentAgentByProductType":64}],"nds10":0,"nds18":0,"ndsNo":25600,"fnsUrl":"www.nalog.gov.ru","region":"50","userInn":"7704340310  ","dateTime":"2025-01-28T03:49:00","kktRegId":"0007411468014909    ","metadata":{"id":5671124923767742720,"ofdId":"ofd8","address":"141281,Россия,Московская область,Пушкинский г.о.,,Ивантеевка город,,Заречная улица,,дом 1,,,,","subtype":"receipt","receiveDate":"2025-01-28T00:49:45Z"},"nds10110":0,"nds18118":0,"totalSum":25600,"creditSum":0,"numberKkt":"00000003820061941985","fiscalSign":812641762,"prepaidSum":0,"properties":{"propertyName":"psp_payment_id","propertyValue":"payment_5f58d4e03e064620ac23413c3bdc813f|authorization_0000"},"retailPlace":"taxi.yandex.ru","shiftNumber":219,"cashTotalSum":0,"internetSign":1,"provisionSum":0,"ecashTotalSum":25600,"machineNumber":"whitespirit4e","operationType":1,"redefine_mask":0,"requestNumber":758,"sellerAddress":"support@go.yandex.com","propertiesData":"ws:CP7KAWYT2N","fiscalDriveNumber":"7384440800300627","messageFiscalSign":9.297239232336366e+18,"retailPlaceAddress":"600902, Россия, Владимирская обл., г. Владимир, микрорайон Энергетик, улица Поисковая, дом 1, корпус 3","appliedTaxationType":1,"buyerPhoneOrAddress":"+79833461053","fiscalDocumentNumber":195702,"fiscalDocumentFormatVer":4,"user_data":{"id":"27853549","promo_id":"","date_scan":"2025-02-07 10:26:28","date_create":""},"taxationType":1}}}}]