[{"_id":"c95b9b32cf2cb9ccd1b0b70a","createdAt":"2025-07-26T11:13:00+03:00","ticket":{"document":{"receipt":{"code":3,"user":"ООО \"Камелот-А\"","items":[{"nds":2,"sum":9894,"name":"Круассан с малиной 63г","price":3298,"quantity":3,"paymentType":4,"productType":1,"itemsQuantityMeasure":0}],"nds10":899,"fnsUrl":"www.nalog.gov.ru","region":"70","userInn":"7017187800  ","dateTime":"2025-07-26T11:13:00","kktRegId":"0006339698003580    ","metadata":{"id":5930799905835585280,"ofdId":"ofd9","address":"634033,Россия,Томская область,город Томск г.о.,,Томск г,,Богдана Хмельницкого пер,,д. 12а,,,помещение ц071-076, ц080-081, ц084,","subtype":"receipt","receiveDate":"2025-07-26T04:13:36Z"},"operator":"Кассир: Шумакова М. В.","totalSum":9894,"creditSum":0,"numberKkt":"0508010012062909","fiscalSign":674409356,"prepaidSum":0,"properties":{"propertyName":"ДанныеБезналичногоЧека","propertyValue":"7707083893;RRN;520749771187"},"retailPlace":"Магазин Ярче","shiftNumber":386,"cashTotalSum":0,"provisionSum":0,"ecashTotalSum":9894,"operationType":1,"redefine_mask":0,"requestNumber":11,"fiscalDriveNumber":"7281440701544240","messageFiscalSign":9.297288675258812e+18,"retailPlaceAddress":"634033, Томская область, г Томск, пер Богдана Хмельницкого, д. 12а помещение ц071-076, ц080-081, 084","appliedTaxationType":1,"fiscalDocumentNumber":80422,"fiscalDocumentFormatVer":4,"user_data":{"id":"30928708","promo_id":"","date_scan":"2025-07-27 05:32:23","date_create":""},"taxationType":1}}}}]