[{"_id":"24b6654b7db747b0b9d8b819","createdAt":"2025-10-06T17:42:00+03:00","ticket":{"document":{"receipt":{"code":3,"user":"ООО \"Камелот-А\"","items":[{"nds":2,"sum":16999,"name":"Сыр Гауда Cheese House 180г 20%","price":16999,"quantity":1,"paymentType":4,"productType":33,"productCodeNew":{"gs1m":{"gtin":"04607028308413","sernum":"5UhM'7","productIdType":6,"rawProductCode":"0104607028308413215UhM'7"}},"labelCodeProcesMode":0,"itemsIndustryDetails":[{"idFoiv":"030","industryPropValue":"UUID=4a315ac7-e7c5-4ac6-a16d-d9d25d11e243&Time=1759747267946","foundationDocNumber":"1944","foundationDocDateTime":"21.11.2023"}],"itemsQuantityMeasure":0,"checkingProdInformationResult":15},{"nds":2,"sum":3999,"name":"Семечки Бабкины жареные 100г","price":3999,"quantity":1,"paymentType":4,"productType":1,"itemsQuantityMeasure":0},{"nds":1,"sum":5399,"name":"Арахис жареный соленый 90г","price":5399,"quantity":1,"paymentType":4,"productType":1,"itemsQuantityMeasure":0}],"nds10":1909,"nds18":900,"fnsUrl":"www.nalog.gov.ru","region":"70","userInn":"7017187800  ","dateTime":"2025-10-06T17:42:00","kktRegId":"0006811749060832    ","metadata":{"id":6035557879864065537,"ofdId":"ofd9","address":"634033,Россия,Томская область,город Томск г.о.,,Томск г,,Богдана Хмельницкого пер,,д. 12а,,,помещение ц071-076, ц080-081, ц084,","subtype":"receipt","receiveDate":"2025-10-06T10:41:20Z"},"operator":"Кассир: Мурманский Г. С.","totalSum":26397,"creditSum":0,"numberKkt":"0250050012032553","fiscalSign":220863150,"prepaidSum":0,"properties":{"propertyName":"ДанныеБезналичногоЧека","propertyValue":"7707083893;RRN;527983789700"},"retailPlace":"Магазин \"Ярче\"","shiftNumber":368,"cashTotalSum":0,"provisionSum":0,"ecashTotalSum":26397,"operationType":1,"redefine_mask":0,"requestNumber":426,"fiscalDriveNumber":"7284440700466325","messageFiscalSign":9.297170158994418e+18,"retailPlaceAddress":"634033, Томская область, г. Томск, пер Богдана Хмельницкого, д.12а, помещение ц071-076, ц080-081, ц084","appliedTaxationType":1,"fiscalDocumentNumber":238639,"fiscalDocumentFormatVer":4,"checkingLabeledProdResult":0,"user_data":{"id":"32245395","promo_id":"","date_scan":"2025-10-06 15:17:53","date_create":""},"taxationType":1}}}}]