[{"_id":"8dcaacf9db182ca60b8d7b55","createdAt":"2025-09-05T08:57:00+03:00","ticket":{"document":{"receipt":{"code":3,"user":"ООО \"Камелот-А\"","items":[{"nds":1,"sum":800,"name":"Пакет-майка ПНД 40х64 30мкм \"Акции ЯРЧЕ\"","price":800,"quantity":1,"paymentType":4,"productType":1,"itemsQuantityMeasure":0},{"nds":2,"sum":8999,"name":"Молоко СТМ цельное ПЭТ 850г","price":8999,"quantity":1,"paymentType":4,"productType":33,"productCodeNew":{"gs1m":{"gtin":"04607080083327","sernum":"5\/I7C&","productIdType":6,"rawProductCode":"0104607080083327215\/I7C&"}},"labelCodeProcesMode":0,"itemsIndustryDetails":[{"idFoiv":"030","industryPropValue":"UUID=926eb12b-c6dd-4c53-a384-5c83e7a7ecd1&Time=1757037362808","foundationDocNumber":"1944","foundationDocDateTime":"21.11.2023"}],"itemsQuantityMeasure":0,"checkingProdInformationResult":15},{"nds":2,"sum":7499,"name":"Бифидок Деревенское молочко 2,5% пюр-пак 500г","price":7499,"quantity":1,"paymentType":4,"productType":33,"productCodeNew":{"gs1m":{"gtin":"04607080083266","sernum":"5QmhFb","productIdType":6,"rawProductCode":"0104607080083266215QmhFb"}},"labelCodeProcesMode":0,"itemsIndustryDetails":[{"idFoiv":"030","industryPropValue":"UUID=d6e13cfe-42f3-486e-8aef-3d8c8c8288b5&Time=1757037369863","foundationDocNumber":"1944","foundationDocDateTime":"21.11.2023"}],"itemsQuantityMeasure":0,"checkingProdInformationResult":15},{"nds":2,"sum":10499,"name":"Сметана СТМ 20% 350г пл\/стакан","price":10499,"quantity":1,"paymentType":4,"productType":33,"productCodeNew":{"gs1m":{"gtin":"04602986013218","sernum":"5QQVNX","productIdType":6,"rawProductCode":"0104602986013218215QQVNX"}},"labelCodeProcesMode":0,"itemsIndustryDetails":[{"idFoiv":"030","industryPropValue":"UUID=1dc26df1-24c4-44ff-a9c4-7bfd3f48cb80&Time=1757037373731","foundationDocNumber":"1944","foundationDocDateTime":"21.11.2023"}],"itemsQuantityMeasure":0,"checkingProdInformationResult":15},{"nds":2,"sum":11999,"name":"Шпроты в масле из кильки каспийской LAATSA 160г","price":11999,"quantity":1,"paymentType":4,"productType":1,"itemsQuantityMeasure":0},{"nds":2,"sum":11591,"name":"Апельсины","price":13999,"quantity":0.828,"paymentType":4,"productType":1,"itemsQuantityMeasure":11},{"nds":2,"sum":3720,"name":"Яблоки свежий урожай","price":9999,"quantity":0.372,"paymentType":4,"productType":1,"itemsQuantityMeasure":11},{"nds":2,"sum":4824,"name":"Груша Хрустальная","price":17999,"quantity":0.268,"paymentType":4,"productType":1,"itemsQuantityMeasure":11},{"nds":2,"sum":4556,"name":"Нектарин","price":16999,"quantity":0.268,"paymentType":4,"productType":1,"itemsQuantityMeasure":11},{"nds":2,"sum":1760,"name":"Огурцы гладкие АКЦИЯ","price":7999,"quantity":0.22,"paymentType":4,"productType":1,"itemsQuantityMeasure":11},{"nds":1,"sum":5399,"name":"Арахис жареный соленый 90г","price":5399,"quantity":1,"paymentType":4,"productType":1,"itemsQuantityMeasure":0},{"nds":2,"sum":2340,"name":"Томаты розовые","price":12999,"quantity":0.18,"paymentType":4,"productType":1,"itemsQuantityMeasure":11},{"nds":2,"sum":4998,"name":"Хлеб на сыворотке особый 300г","price":4998,"quantity":1,"paymentType":4,"productType":1,"itemsQuantityMeasure":0},{"nds":2,"sum":6498,"name":"Хлеб бездрож.форм гречневый 400г","price":6498,"quantity":1,"paymentType":4,"productType":1,"itemsQuantityMeasure":0},{"nds":2,"sum":8999,"name":"Яйцо куриное С0 (10шт)","price":8999,"quantity":1,"paymentType":4,"productType":1,"itemsQuantityMeasure":0}],"nds10":8026,"nds18":1033,"fnsUrl":"www.nalog.gov.ru","region":"70","userInn":"7017187800  ","dateTime":"2025-09-05T08:57:00","kktRegId":"0006208103058876    ","metadata":{"id":5990094478090318336,"ofdId":"ofd9","address":"634033,Россия,Томская область,город Томск г.о.,,Томск г,,Богдана Хмельницкого пер,,д. 12а,,,помещение ц071-076, ц080-081, ц084,","subtype":"receipt","receiveDate":"2025-09-05T01:57:30Z"},"operator":"Кассир: Кирилюк А. А.","totalSum":94481,"creditSum":0,"numberKkt":"0316910012230605","fiscalSign":3084226775,"prepaidSum":0,"properties":{"propertyName":"ДанныеБезналичногоЧека","propertyValue":"7707083893;RRN;524819040276"},"retailPlace":"Магазин Ярче","shiftNumber":166,"cashTotalSum":0,"provisionSum":0,"ecashTotalSum":94481,"operationType":1,"redefine_mask":0,"requestNumber":84,"fiscalDriveNumber":"7380440801716924","messageFiscalSign":9.2973933599997e+18,"retailPlaceAddress":"634033, Томская область, г Томск, пер Богдана Хмельницкого,д. 12а помещение ц071-076, ц080-081, ц084","appliedTaxationType":1,"fiscalDocumentNumber":32719,"fiscalDocumentFormatVer":4,"checkingLabeledProdResult":0,"user_data":{"id":"31728476","promo_id":"","date_scan":"2025-09-12 03:43:14","date_create":""},"taxationType":1}}}}]