[{"_id":"980bcc19e364357eb7cf1257","createdAt":"2025-10-16T06:10:00+03:00","ticket":{"document":{"receipt":{"code":3,"nds0":0,"user":"ОБЩЕСТВО С ОГРАНИЧЕННОЙ ОТВЕТСТВЕННОСТЬЮ \"Яндекс Маркет\"","items":[{"nds":6,"sum":70200,"name":"Мешок для стирки деликатных вещей обуви и игрушек","price":35100,"quantity":2,"paymentType":1,"productType":1,"providerInn":"236402487848","labelCodeProcesMode":0,"itemsQuantityMeasure":0,"paymentAgentByProductType":64}],"nds10":0,"nds18":0,"ndsNo":70200,"fnsUrl":"www.nalog.gov.ru","region":"62","userInn":"9704254424  ","dateTime":"2025-10-16T06:10:00","kktRegId":"0009188543061670    ","metadata":{"id":6049599667639792896,"ofdId":"ofd8","address":"391434,Россия,Рязанская область,Сасовский г.о.,,Сасово город,,Пушкина улица,,дом 21,,,,","subtype":"receipt","receiveDate":"2025-10-16T03:10:38Z"},"nds10110":0,"nds18118":0,"totalSum":70200,"creditSum":0,"numberKkt":"00000003810544702120","fiscalSign":3921959273,"prepaidSum":0,"properties":{"propertyName":"psp_payment_id","propertyValue":"payment_f187b40bf0c2453180512fa5cb7b911c|authorization_0000"},"retailPlace":"market.yandex.ru","shiftNumber":216,"cashTotalSum":0,"internetSign":1,"provisionSum":0,"ecashTotalSum":70200,"machineNumber":"whitespirit4h","operationType":1,"redefine_mask":0,"requestNumber":86,"sellerAddress":"order@market.yandex.ru","propertiesData":"ws:CHLJWCUR4Y","internetPayment":1,"fiscalDriveNumber":"7380440902203450","messageFiscalSign":9.297397957902815e+18,"retailPlaceAddress":"391430, Россия, Рязанская обл., г. Сасово, ул. Пушкина, д. 21","appliedTaxationType":1,"buyerPhoneOrAddress":"staritsyn@mail.ru","fiscalDocumentNumber":206469,"fiscalDocumentFormatVer":4,"user_data":{"id":"32471963","promo_id":"","date_scan":"2025-10-17 07:59:08","date_create":""},"taxationType":1}}}}]